hyperview/__init__.py
hyperview/_version.py
hyperview/api.py
hyperview/cli.py
hyperview/core/__init__.py
hyperview/core/dataset.py
hyperview/core/sample.py
hyperview/core/selection.py
hyperview/embeddings/__init__.py
hyperview/embeddings/compute.py
hyperview/embeddings/engine.py
hyperview/embeddings/pipelines.py
hyperview/embeddings/projection.py
hyperview/embeddings/providers/__init__.py
hyperview/embeddings/providers/lancedb_providers.py
hyperview/server/__init__.py
hyperview/server/app.py
hyperview/server/static/404.html
hyperview/server/static/__next.__PAGE__.txt
hyperview/server/static/__next._full.txt
hyperview/server/static/__next._head.txt
hyperview/server/static/__next._index.txt
hyperview/server/static/__next._tree.txt
hyperview/server/static/index.html
hyperview/server/static/index.txt
hyperview/server/static/404/index.html
hyperview/server/static/_next/static/9UIGNc82PJ8k2Tsn68di9/_buildManifest.js
hyperview/server/static/_next/static/9UIGNc82PJ8k2Tsn68di9/_clientMiddlewareManifest.json
hyperview/server/static/_next/static/9UIGNc82PJ8k2Tsn68di9/_ssgManifest.js
hyperview/server/static/_next/static/chunks/3098f127ca49563b.js
hyperview/server/static/_next/static/chunks/4543baba6321cb86.js
hyperview/server/static/_next/static/chunks/567993cf36cd4ab1.js
hyperview/server/static/_next/static/chunks/80cd550edf03d788.js
hyperview/server/static/_next/static/chunks/86c1fc4cf542f408.js
hyperview/server/static/_next/static/chunks/a6dad97d9634a72d.js
hyperview/server/static/_next/static/chunks/a6dad97d9634a72d.js.map
hyperview/server/static/_next/static/chunks/e7ae0fd4a43b4ae1.css
hyperview/server/static/_next/static/chunks/e954ba82c0a04100.js
hyperview/server/static/_next/static/chunks/f29dd35a99c216ea.js
hyperview/server/static/_next/static/chunks/turbopack-cb59e03a04a579d1.js
hyperview/server/static/_next/static/media/1bffadaabf893a1e-s.7cd81963.woff2
hyperview/server/static/_next/static/media/2bbe8d2671613f1f-s.76dcb0b2.woff2
hyperview-0.1.1.dist-info/METADATA
hyperview-0.1.1.dist-info/WHEEL
hyperview-0.1.1.dist-info/entry_points.txt
hyperview-0.1.1.dist-info/licenses/LICENSE
hyperview-0.1.1.dist-info/RECORD
