Metadata-Version: 2.4
Name: hyperview
Version: 0.1.1
Summary: Open-source dataset curation with hyperbolic embeddings visualization
Project-URL: Homepage, https://github.com/Hyper3Labs/HyperView
Project-URL: Documentation, https://github.com/Hyper3Labs/HyperView#readme
Project-URL: Repository, https://github.com/Hyper3Labs/HyperView
Project-URL: Issues, https://github.com/Hyper3Labs/HyperView/issues
Author: hyper3labs
License: MIT
License-File: LICENSE
Keywords: curation,dataset,embeddings,hyperbolic,machine-learning,visualization
Classifier: Development Status :: 3 - Alpha
Classifier: Intended Audience :: Developers
Classifier: Intended Audience :: Science/Research
Classifier: License :: OSI Approved :: MIT License
Classifier: Programming Language :: Python :: 3
Classifier: Programming Language :: Python :: 3.10
Classifier: Programming Language :: Python :: 3.11
Classifier: Programming Language :: Python :: 3.12
Classifier: Topic :: Scientific/Engineering :: Artificial Intelligence
Classifier: Topic :: Scientific/Engineering :: Visualization
Requires-Python: >=3.10
Requires-Dist: aiofiles>=25.1.0
Requires-Dist: datasets>=4.5.0
Requires-Dist: embed-anything>=0.7.0
Requires-Dist: fastapi>=0.128.0
Requires-Dist: hyper-models>=0.1.0
Requires-Dist: lancedb>=0.26.1
Requires-Dist: numpy<2.4,>=1.26.4
Requires-Dist: pillow>=12.1.0
Requires-Dist: pyarrow>=22.0.0
Requires-Dist: pydantic>=2.12.5
Requires-Dist: umap-learn>=0.5.11
Requires-Dist: uvicorn[standard]>=0.40.0
Provides-Extra: dev
Requires-Dist: httpx>=0.28.1; extra == 'dev'
Requires-Dist: pytest-asyncio>=1.3.0; extra == 'dev'
Requires-Dist: pytest>=9.0.2; extra == 'dev'
Requires-Dist: ruff>=0.14.13; extra == 'dev'
Provides-Extra: ml
Requires-Dist: timm>=1.0.0; extra == 'ml'
Requires-Dist: torch>=2.9.1; extra == 'ml'
Requires-Dist: torchvision>=0.24.1; extra == 'ml'
